README.md
setup.py
pgen2/__init__.py
pgen2/dfa.py
pgen2/parser.py
pgen2/pgen.py
pgen2/tokenizer.py
pgen2.egg-info/PKG-INFO
pgen2.egg-info/SOURCES.txt
pgen2.egg-info/dependency_links.txt
pgen2.egg-info/top_level.txt