Metadata-Version: 2.1
Name: pgen2
Version: 0.1.1
Summary: Pure Python implementation of pgen, the Python parser generator
Home-page: https://github.com/mythonlang/pgen2/
Author: Jon Riehl
Author-email: jon.riehl@gmail.com
License: UNKNOWN
Keywords: parser,generator
Platform: UNKNOWN
Classifier: Programming Language :: Python
Classifier: Programming Language :: Python :: 2.7
Classifier: Programming Language :: Python :: 3
Classifier: Development Status :: 4 - Beta
Classifier: Environment :: Other Environment
Classifier: Intended Audience :: Developers
Classifier: License :: OSI Approved :: BSD License
Classifier: Operating System :: OS Independent
Classifier: Topic :: Software Development
Classifier: Topic :: Software Development :: Libraries :: Python Modules
